{
  "test_periods": 100,
  "single": {
    "description": "单式 (6红1蓝)",
    "red_count": 6,
    "blue_count": 1,
    "random_baseline": 1.0907,
    "strategies": {
      "智能加权": {
        "avg_red_match": 0.87,
        "blue_accuracy": 0.04,
        "distribution": {
          "0": 31,
          "2": 16,
          "1": 52,
          "3": 1
        },
        "details": [
          {
            "period": "2026037",
            "predicted_red": [
              1,
              12,
              17,
              23,
              31,
              32
            ],
            "predicted_blue": 9,
            "actual_red": [
              11,
              22,
              27,
              29,
              31,
              33
            ],
            "actual_blue": 12,
            "red_match": 1,
            "blue_match": 0,
            "prize": null,
            "prize_amount": 0,
            "fortune_eligible": false,
            "fortune_amount": 0
          },
          {
            "period": "2026038",
            "predicted_red": [
              1,
              8,
              13,
              24,
              26,
              30
            ],
            "predicted_blue": 15,
            "actual_red": [
              1,
              2,
              13,
              23,
              25,
              27
            ],
            "actual_blue": 5,
            "red_match": 2,
            "blue_match": 0,
            "prize": null,
            "prize_amount": 0,
            "fortune_eligible": false,
            "fortune_amount": 0
          },
          {
            "period": "2026039",
            "predicted_red": [
              1,
              2,
              18,
              24,
              26,
              28
            ],
            "predicted_blue": 9,
            "actual_red": [
              8,
              17,
              18,
              21,
              25,
              30
            ],
            "actual_blue": 5,
            "red_match": 1,
            "blue_match": 0,
            "prize": null,
            "prize_amount": 0,
            "fortune_eligible": false,
            "fortune_amount": 0
          },
          {
            "period": "2026040",
            "predicted_red": [
              2,
              8,
              13,
              21,
              22,
              32
            ],
            "predicted_blue": 4,
            "actual_red": [
              3,
              4,
              14,
              22,
              23,
              33
            ],
            "actual_blue": 4,
            "red_match": 1,
            "blue_match": 1,
            "prize": "六等奖",
            "prize_amount": 5,
            "fortune_eligible": false,
            "fortune_amount": 0
          },
          {
            "period": "2026041",
            "predicted_red": [
              1,
              3,
              4,
              11,
              16,
              28
            ],
            "predicted_blue": 16,
            "actual_red": [
              2,
              8,
              10,
              17,
              19,
              24
            ],
            "actual_blue": 13,
            "red_match": 0,
            "blue_match": 0,
            "prize": null,
            "prize_amount": 0,
            "fortune_eligible": false,
            "fortune_amount": 0
          }
        ]
      },
      "三区均衡": {
        "avg_red_match": 1.18,
        "blue_accuracy": 0.1,
        "distribution": {
          "0": 22,
          "1": 46,
          "3": 6,
          "2": 25,
          "4": 1
        },
        "details": [
          {
            "period": "2026037",
            "predicted_red": [
              4,
              11,
              13,
              14,
              24,
              29
            ],
            "predicted_blue": 13,
            "actual_red": [
              11,
              22,
              27,
              29,
              31,
              33
            ],
            "actual_blue": 12,
            "red_match": 2,
            "blue_match": 0,
            "prize": null,
            "prize_amount": 0,
            "fortune_eligible": false,
            "fortune_amount": 0
          },
          {
            "period": "2026038",
            "predicted_red": [
              6,
              7,
              14,
              17,
              31,
              33
            ],
            "predicted_blue": 13,
            "actual_red": [
              1,
              2,
              13,
              23,
              25,
              27
            ],
            "actual_blue": 5,
            "red_match": 0,
            "blue_match": 0,
            "prize": null,
            "prize_amount": 0,
            "fortune_eligible": false,
            "fortune_amount": 0
          },
          {
            "period": "2026039",
            "predicted_red": [
              3,
              9,
              19,
              21,
              28,
              33
            ],
            "predicted_blue": 11,
            "actual_red": [
              8,
              17,
              18,
              21,
              25,
              30
            ],
            "actual_blue": 5,
            "red_match": 1,
            "blue_match": 0,
            "prize": null,
            "prize_amount": 0,
            "fortune_eligible": false,
            "fortune_amount": 0
          },
          {
            "period": "2026040",
            "predicted_red": [
              1,
              9,
              12,
              22,
              25,
              27
            ],
            "predicted_blue": 12,
            "actual_red": [
              3,
              4,
              14,
              22,
              23,
              33
            ],
            "actual_blue": 4,
            "red_match": 1,
            "blue_match": 0,
            "prize": null,
            "prize_amount": 0,
            "fortune_eligible": false,
            "fortune_amount": 0
          },
          {
            "period": "2026041",
            "predicted_red": [
              4,
              8,
              13,
              17,
              27,
              32
            ],
            "predicted_blue": 9,
            "actual_red": [
              2,
              8,
              10,
              17,
              19,
              24
            ],
            "actual_blue": 13,
            "red_match": 2,
            "blue_match": 0,
            "prize": null,
            "prize_amount": 0,
            "fortune_eligible": false,
            "fortune_amount": 0
          }
        ]
      },
      "冷热混合": {
        "avg_red_match": 1.07,
        "blue_accuracy": 0.04,
        "distribution": {
          "0": 31,
          "2": 20,
          "3": 9,
          "1": 40
        },
        "details": [
          {
            "period": "2026037",
            "predicted_red": [
              2,
              13,
              17,
              28,
              30,
              32
            ],
            "predicted_blue": 9,
            "actual_red": [
              11,
              22,
              27,
              29,
              31,
              33
            ],
            "actual_blue": 12,
            "red_match": 0,
            "blue_match": 0,
            "prize": null,
            "prize_amount": 0,
            "fortune_eligible": false,
            "fortune_amount": 0
          },
          {
            "period": "2026038",
            "predicted_red": [
              3,
              7,
              13,
              14,
              22,
              32
            ],
            "predicted_blue": 4,
            "actual_red": [
              1,
              2,
              13,
              23,
              25,
              27
            ],
            "actual_blue": 5,
            "red_match": 1,
            "blue_match": 0,
            "prize": null,
            "prize_amount": 0,
            "fortune_eligible": false,
            "fortune_amount": 0
          },
          {
            "period": "2026039",
            "predicted_red": [
              2,
              12,
              13,
              14,
              23,
              31
            ],
            "predicted_blue": 10,
            "actual_red": [
              8,
              17,
              18,
              21,
              25,
              30
            ],
            "actual_blue": 5,
            "red_match": 0,
            "blue_match": 0,
            "prize": null,
            "prize_amount": 0,
            "fortune_eligible": false,
            "fortune_amount": 0
          },
          {
            "period": "2026040",
            "predicted_red": [
              2,
              4,
              9,
              15,
              27,
              33
            ],
            "predicted_blue": 6,
            "actual_red": [
              3,
              4,
              14,
              22,
              23,
              33
            ],
            "actual_blue": 4,
            "red_match": 2,
            "blue_match": 0,
            "prize": null,
            "prize_amount": 0,
            "fortune_eligible": false,
            "fortune_amount": 0
          },
          {
            "period": "2026041",
            "predicted_red": [
              1,
              2,
              4,
              14,
              23,
              31
            ],
            "predicted_blue": 4,
            "actual_red": [
              2,
              8,
              10,
              17,
              19,
              24
            ],
            "actual_blue": 13,
            "red_match": 1,
            "blue_match": 0,
            "prize": null,
            "prize_amount": 0,
            "fortune_eligible": false,
            "fortune_amount": 0
          }
        ]
      },
      "遗漏优先": {
        "avg_red_match": 0.91,
        "blue_accuracy": 0.09,
        "distribution": {
          "0": 34,
          "1": 45,
          "2": 17,
          "3": 4
        },
        "details": [
          {
            "period": "2026037",
            "predicted_red": [
              4,
              5,
              8,
              9,
              20,
              30
            ],
            "predicted_blue": 1,
            "actual_red": [
              11,
              22,
              27,
              29,
              31,
              33
            ],
            "actual_blue": 12,
            "red_match": 0,
            "blue_match": 0,
            "prize": null,
            "prize_amount": 0,
            "fortune_eligible": false,
            "fortune_amount": 0
          },
          {
            "period": "2026038",
            "predicted_red": [
              4,
              9,
              14,
              17,
              20,
              26
            ],
            "predicted_blue": 11,
            "actual_red": [
              1,
              2,
              13,
              23,
              25,
              27
            ],
            "actual_blue": 5,
            "red_match": 0,
            "blue_match": 0,
            "prize": null,
            "prize_amount": 0,
            "fortune_eligible": false,
            "fortune_amount": 0
          },
          {
            "period": "2026039",
            "predicted_red": [
              4,
              5,
              14,
              16,
              17,
              20
            ],
            "predicted_blue": 11,
            "actual_red": [
              8,
              17,
              18,
              21,
              25,
              30
            ],
            "actual_blue": 5,
            "red_match": 1,
            "blue_match": 0,
            "prize": null,
            "prize_amount": 0,
            "fortune_eligible": false,
            "fortune_amount": 0
          },
          {
            "period": "2026040",
            "predicted_red": [
              4,
              5,
              7,
              14,
              19,
              26
            ],
            "predicted_blue": 1,
            "actual_red": [
              3,
              4,
              14,
              22,
              23,
              33
            ],
            "actual_blue": 4,
            "red_match": 2,
            "blue_match": 0,
            "prize": null,
            "prize_amount": 0,
            "fortune_eligible": false,
            "fortune_amount": 0
          },
          {
            "period": "2026041",
            "predicted_red": [
              5,
              7,
              9,
              19,
              20,
              24
            ],
            "predicted_blue": 9,
            "actual_red": [
              2,
              8,
              10,
              17,
              19,
              24
            ],
            "actual_blue": 13,
            "red_match": 2,
            "blue_match": 0,
            "prize": null,
            "prize_amount": 0,
            "fortune_eligible": false,
            "fortune_amount": 0
          }
        ]
      },
      "和值控制": {
        "avg_red_match": 1.09,
        "blue_accuracy": 0.08,
        "distribution": {
          "2": 21,
          "0": 32,
          "1": 38,
          "3": 7,
          "4": 2
        },
        "details": [
          {
            "period": "2026037",
            "predicted_red": [
              1,
              4,
              9,
              22,
              25,
              33
            ],
            "predicted_blue": 3,
            "actual_red": [
              11,
              22,
              27,
              29,
              31,
              33
            ],
            "actual_blue": 12,
            "red_match": 2,
            "blue_match": 0,
            "prize": null,
            "prize_amount": 0,
            "fortune_eligible": false,
            "fortune_amount": 0
          },
          {
            "period": "2026038",
            "predicted_red": [
              6,
              7,
              9,
              15,
              18,
              23
            ],
            "predicted_blue": 12,
            "actual_red": [
              1,
              2,
              13,
              23,
              25,
              27
            ],
            "actual_blue": 5,
            "red_match": 1,
            "blue_match": 0,
            "prize": null,
            "prize_amount": 0,
            "fortune_eligible": false,
            "fortune_amount": 0
          },
          {
            "period": "2026039",
            "predicted_red": [
              7,
              8,
              10,
              24,
              27,
              31
            ],
            "predicted_blue": 8,
            "actual_red": [
              8,
              17,
              18,
              21,
              25,
              30
            ],
            "actual_blue": 5,
            "red_match": 1,
            "blue_match": 0,
            "prize": null,
            "prize_amount": 0,
            "fortune_eligible": false,
            "fortune_amount": 0
          },
          {
            "period": "2026040",
            "predicted_red": [
              6,
              8,
              9,
              24,
              28,
              29
            ],
            "predicted_blue": 7,
            "actual_red": [
              3,
              4,
              14,
              22,
              23,
              33
            ],
            "actual_blue": 4,
            "red_match": 0,
            "blue_match": 0,
            "prize": null,
            "prize_amount": 0,
            "fortune_eligible": false,
            "fortune_amount": 0
          },
          {
            "period": "2026041",
            "predicted_red": [
              1,
              7,
              8,
              23,
              24,
              25
            ],
            "predicted_blue": 16,
            "actual_red": [
              2,
              8,
              10,
              17,
              19,
              24
            ],
            "actual_blue": 13,
            "red_match": 2,
            "blue_match": 0,
            "prize": null,
            "prize_amount": 0,
            "fortune_eligible": false,
            "fortune_amount": 0
          }
        ]
      },
      "连号感知": {
        "avg_red_match": 1.26,
        "blue_accuracy": 0.02,
        "distribution": {
          "1": 41,
          "2": 24,
          "0": 23,
          "3": 11,
          "4": 1
        },
        "details": [
          {
            "period": "2026037",
            "predicted_red": [
              3,
              9,
              18,
              22,
              23,
              24
            ],
            "predicted_blue": 16,
            "actual_red": [
              11,
              22,
              27,
              29,
              31,
              33
            ],
            "actual_blue": 12,
            "red_match": 1,
            "blue_match": 0,
            "prize": null,
            "prize_amount": 0,
            "fortune_eligible": false,
            "fortune_amount": 0
          },
          {
            "period": "2026038",
            "predicted_red": [
              3,
              10,
              11,
              22,
              26,
              30
            ],
            "predicted_blue": 10,
            "actual_red": [
              1,
              2,
              13,
              23,
              25,
              27
            ],
            "actual_blue": 5,
            "red_match": 0,
            "blue_match": 0,
            "prize": null,
            "prize_amount": 0,
            "fortune_eligible": false,
            "fortune_amount": 0
          },
          {
            "period": "2026039",
            "predicted_red": [
              7,
              17,
              18,
              21,
              22,
              23
            ],
            "predicted_blue": 6,
            "actual_red": [
              8,
              17,
              18,
              21,
              25,
              30
            ],
            "actual_blue": 5,
            "red_match": 3,
            "blue_match": 0,
            "prize": null,
            "prize_amount": 0,
            "fortune_eligible": true,
            "fortune_amount": 5
          },
          {
            "period": "2026040",
            "predicted_red": [
              3,
              16,
              22,
              23,
              27,
              32
            ],
            "predicted_blue": 14,
            "actual_red": [
              3,
              4,
              14,
              22,
              23,
              33
            ],
            "actual_blue": 4,
            "red_match": 3,
            "blue_match": 0,
            "prize": null,
            "prize_amount": 0,
            "fortune_eligible": true,
            "fortune_amount": 5
          },
          {
            "period": "2026041",
            "predicted_red": [
              2,
              8,
              11,
              12,
              19,
              33
            ],
            "predicted_blue": 1,
            "actual_red": [
              2,
              8,
              10,
              17,
              19,
              24
            ],
            "actual_blue": 13,
            "red_match": 3,
            "blue_match": 0,
            "prize": null,
            "prize_amount": 0,
            "fortune_eligible": true,
            "fortune_amount": 5
          }
        ]
      }
    },
    "best_strategy": {
      "name": "连号感知",
      "avg_red_match": 1.26,
      "improvement": 0.1693
    },
    "ranking": [
      [
        "连号感知",
        1.26
      ],
      [
        "三区均衡",
        1.18
      ],
      [
        "和值控制",
        1.09
      ],
      [
        "冷热混合",
        1.07
      ],
      [
        "遗漏优先",
        0.91
      ],
      [
        "智能加权",
        0.87
      ]
    ]
  },
  "duplex": {
    "description": "复式 (7红3蓝)",
    "red_count": 7,
    "blue_count": 3,
    "random_baseline": 1.2754,
    "strategies": {
      "智能加权": {
        "avg_red_match": 1.15,
        "blue_accuracy": 0.19,
        "distribution": {
          "2": 20,
          "1": 48,
          "0": 23,
          "3": 9
        },
        "details": [
          {
            "period": "2026037",
            "predicted_red": [
              2,
              6,
              8,
              12,
              16,
              24,
              30
            ],
            "predicted_blue": [
              4,
              9,
              15
            ],
            "actual_red": [
              11,
              22,
              27,
              29,
              31,
              33
            ],
            "actual_blue": 12,
            "red_match": 0,
            "blue_match": 0,
            "prize": null,
            "prize_amount": 0,
            "fortune_eligible": false,
            "fortune_amount": 0
          },
          {
            "period": "2026038",
            "predicted_red": [
              6,
              11,
              15,
              19,
              25,
              29,
              30
            ],
            "predicted_blue": [
              1,
              2,
              13
            ],
            "actual_red": [
              1,
              2,
              13,
              23,
              25,
              27
            ],
            "actual_blue": 5,
            "red_match": 1,
            "blue_match": 0,
            "prize": null,
            "prize_amount": 0,
            "fortune_eligible": false,
            "fortune_amount": 0
          },
          {
            "period": "2026039",
            "predicted_red": [
              6,
              7,
              9,
              11,
              12,
              18,
              27
            ],
            "predicted_blue": [
              1,
              2,
              14
            ],
            "actual_red": [
              8,
              17,
              18,
              21,
              25,
              30
            ],
            "actual_blue": 5,
            "red_match": 1,
            "blue_match": 0,
            "prize": null,
            "prize_amount": 0,
            "fortune_eligible": false,
            "fortune_amount": 0
          },
          {
            "period": "2026040",
            "predicted_red": [
              1,
              2,
              7,
              16,
              22,
              29,
              30
            ],
            "predicted_blue": [
              2,
              3,
              8
            ],
            "actual_red": [
              3,
              4,
              14,
              22,
              23,
              33
            ],
            "actual_blue": 4,
            "red_match": 1,
            "blue_match": 0,
            "prize": null,
            "prize_amount": 0,
            "fortune_eligible": false,
            "fortune_amount": 0
          },
          {
            "period": "2026041",
            "predicted_red": [
              3,
              6,
              11,
              14,
              20,
              25,
              28
            ],
            "predicted_blue": [
              1,
              2,
              13
            ],
            "actual_red": [
              2,
              8,
              10,
              17,
              19,
              24
            ],
            "actual_blue": 13,
            "red_match": 0,
            "blue_match": 1,
            "prize": "六等奖(含)",
            "prize_amount": 35,
            "fortune_eligible": false,
            "fortune_amount": 0
          }
        ],
        "fortune_stats": {
          "eligible_rate": 0.07,
          "profit_rate": 0.07,
          "total_fortune": 420,
          "total_cost": 4200,
          "net_fortune": -3780
        }
      },
      "三区均衡": {
        "avg_red_match": 1.22,
        "blue_accuracy": 0.18,
        "distribution": {
          "1": 48,
          "2": 28,
          "0": 18,
          "3": 6
        },
        "details": [
          {
            "period": "2026037",
            "predicted_red": [
              7,
              11,
              14,
              15,
              22,
              26,
              29
            ],
            "predicted_blue": [
              3,
              4,
              6
            ],
            "actual_red": [
              11,
              22,
              27,
              29,
              31,
              33
            ],
            "actual_blue": 12,
            "red_match": 3,
            "blue_match": 0,
            "prize": null,
            "prize_amount": 0,
            "fortune_eligible": true,
            "fortune_amount": 60
          },
          {
            "period": "2026038",
            "predicted_red": [
              4,
              6,
              15,
              17,
              24,
              27,
              33
            ],
            "predicted_blue": [
              7,
              11,
              12
            ],
            "actual_red": [
              1,
              2,
              13,
              23,
              25,
              27
            ],
            "actual_blue": 5,
            "red_match": 1,
            "blue_match": 0,
            "prize": null,
            "prize_amount": 0,
            "fortune_eligible": false,
            "fortune_amount": 0
          },
          {
            "period": "2026039",
            "predicted_red": [
              4,
              10,
              14,
              17,
              22,
              27,
              31
            ],
            "predicted_blue": [
              1,
              10,
              14
            ],
            "actual_red": [
              8,
              17,
              18,
              21,
              25,
              30
            ],
            "actual_blue": 5,
            "red_match": 1,
            "blue_match": 0,
            "prize": null,
            "prize_amount": 0,
            "fortune_eligible": false,
            "fortune_amount": 0
          },
          {
            "period": "2026040",
            "predicted_red": [
              1,
              6,
              12,
              15,
              22,
              25,
              31
            ],
            "predicted_blue": [
              1,
              2,
              5
            ],
            "actual_red": [
              3,
              4,
              14,
              22,
              23,
              33
            ],
            "actual_blue": 4,
            "red_match": 1,
            "blue_match": 0,
            "prize": null,
            "prize_amount": 0,
            "fortune_eligible": false,
            "fortune_amount": 0
          },
          {
            "period": "2026041",
            "predicted_red": [
              3,
              4,
              9,
              12,
              20,
              23,
              31
            ],
            "predicted_blue": [
              11,
              14,
              15
            ],
            "actual_red": [
              2,
              8,
              10,
              17,
              19,
              24
            ],
            "actual_blue": 13,
            "red_match": 0,
            "blue_match": 0,
            "prize": null,
            "prize_amount": 0,
            "fortune_eligible": false,
            "fortune_amount": 0
          }
        ],
        "fortune_stats": {
          "eligible_rate": 0.05,
          "profit_rate": 0.05,
          "total_fortune": 300,
          "total_cost": 4200,
          "net_fortune": -3900
        }
      },
      "冷热混合": {
        "avg_red_match": 1.3,
        "blue_accuracy": 0.22,
        "distribution": {
          "0": 22,
          "1": 45,
          "2": 19,
          "3": 10,
          "4": 3,
          "5": 1
        },
        "details": [
          {
            "period": "2026037",
            "predicted_red": [
              3,
              9,
              11,
              13,
              16,
              31,
              33
            ],
            "predicted_blue": [
              10,
              15,
              16
            ],
            "actual_red": [
              11,
              22,
              27,
              29,
              31,
              33
            ],
            "actual_blue": 12,
            "red_match": 3,
            "blue_match": 0,
            "prize": null,
            "prize_amount": 0,
            "fortune_eligible": true,
            "fortune_amount": 60
          },
          {
            "period": "2026038",
            "predicted_red": [
              8,
              12,
              13,
              19,
              30,
              31,
              32
            ],
            "predicted_blue": [
              1,
              12,
              15
            ],
            "actual_red": [
              1,
              2,
              13,
              23,
              25,
              27
            ],
            "actual_blue": 5,
            "red_match": 1,
            "blue_match": 0,
            "prize": null,
            "prize_amount": 0,
            "fortune_eligible": false,
            "fortune_amount": 0
          },
          {
            "period": "2026039",
            "predicted_red": [
              3,
              4,
              12,
              15,
              26,
              27,
              29
            ],
            "predicted_blue": [
              4,
              9,
              15
            ],
            "actual_red": [
              8,
              17,
              18,
              21,
              25,
              30
            ],
            "actual_blue": 5,
            "red_match": 0,
            "blue_match": 0,
            "prize": null,
            "prize_amount": 0,
            "fortune_eligible": false,
            "fortune_amount": 0
          },
          {
            "period": "2026040",
            "predicted_red": [
              6,
              13,
              19,
              27,
              29,
              30,
              32
            ],
            "predicted_blue": [
              1,
              14,
              16
            ],
            "actual_red": [
              3,
              4,
              14,
              22,
              23,
              33
            ],
            "actual_blue": 4,
            "red_match": 0,
            "blue_match": 0,
            "prize": null,
            "prize_amount": 0,
            "fortune_eligible": false,
            "fortune_amount": 0
          },
          {
            "period": "2026041",
            "predicted_red": [
              2,
              3,
              10,
              16,
              18,
              19,
              23
            ],
            "predicted_blue": [
              5,
              8,
              9
            ],
            "actual_red": [
              2,
              8,
              10,
              17,
              19,
              24
            ],
            "actual_blue": 13,
            "red_match": 3,
            "blue_match": 0,
            "prize": null,
            "prize_amount": 0,
            "fortune_eligible": true,
            "fortune_amount": 60
          }
        ],
        "fortune_stats": {
          "eligible_rate": 0.11,
          "profit_rate": 0.1,
          "total_fortune": 600,
          "total_cost": 4200,
          "net_fortune": -3600
        }
      },
      "遗漏优先": {
        "avg_red_match": 1.2,
        "blue_accuracy": 0.17,
        "distribution": {
          "1": 50,
          "2": 29,
          "0": 17,
          "3": 4
        },
        "details": [
          {
            "period": "2026037",
            "predicted_red": [
              4,
              14,
              16,
              19,
              26,
              27,
              30
            ],
            "predicted_blue": [
              1,
              12,
              14
            ],
            "actual_red": [
              11,
              22,
              27,
              29,
              31,
              33
            ],
            "actual_blue": 12,
            "red_match": 1,
            "blue_match": 1,
            "prize": "六等奖(含)",
            "prize_amount": 35,
            "fortune_eligible": false,
            "fortune_amount": 0
          },
          {
            "period": "2026038",
            "predicted_red": [
              4,
              5,
              9,
              16,
              17,
              18,
              26
            ],
            "predicted_blue": [
              1,
              10,
              11
            ],
            "actual_red": [
              1,
              2,
              13,
              23,
              25,
              27
            ],
            "actual_blue": 5,
            "red_match": 0,
            "blue_match": 0,
            "prize": null,
            "prize_amount": 0,
            "fortune_eligible": false,
            "fortune_amount": 0
          },
          {
            "period": "2026039",
            "predicted_red": [
              4,
              5,
              14,
              16,
              17,
              19,
              20
            ],
            "predicted_blue": [
              11,
              14,
              16
            ],
            "actual_red": [
              8,
              17,
              18,
              21,
              25,
              30
            ],
            "actual_blue": 5,
            "red_match": 1,
            "blue_match": 0,
            "prize": null,
            "prize_amount": 0,
            "fortune_eligible": false,
            "fortune_amount": 0
          },
          {
            "period": "2026040",
            "predicted_red": [
              4,
              5,
              9,
              16,
              19,
              26,
              32
            ],
            "predicted_blue": [
              1,
              10,
              16
            ],
            "actual_red": [
              3,
              4,
              14,
              22,
              23,
              33
            ],
            "actual_blue": 4,
            "red_match": 1,
            "blue_match": 0,
            "prize": null,
            "prize_amount": 0,
            "fortune_eligible": false,
            "fortune_amount": 0
          },
          {
            "period": "2026041",
            "predicted_red": [
              5,
              7,
              10,
              12,
              16,
              19,
              24
            ],
            "predicted_blue": [
              1,
              9,
              14
            ],
            "actual_red": [
              2,
              8,
              10,
              17,
              19,
              24
            ],
            "actual_blue": 13,
            "red_match": 3,
            "blue_match": 0,
            "prize": null,
            "prize_amount": 0,
            "fortune_eligible": true,
            "fortune_amount": 60
          }
        ],
        "fortune_stats": {
          "eligible_rate": 0.04,
          "profit_rate": 0.04,
          "total_fortune": 240,
          "total_cost": 4200,
          "net_fortune": -3960
        }
      },
      "和值控制": {
        "avg_red_match": 1.36,
        "blue_accuracy": 0.17,
        "distribution": {
          "1": 49,
          "2": 24,
          "0": 14,
          "3": 13
        },
        "details": [
          {
            "period": "2026037",
            "predicted_red": [
              6,
              7,
              13,
              15,
              24,
              30,
              31
            ],
            "predicted_blue": [
              5,
              6,
              9
            ],
            "actual_red": [
              11,
              22,
              27,
              29,
              31,
              33
            ],
            "actual_blue": 12,
            "red_match": 1,
            "blue_match": 0,
            "prize": null,
            "prize_amount": 0,
            "fortune_eligible": false,
            "fortune_amount": 0
          },
          {
            "period": "2026038",
            "predicted_red": [
              1,
              6,
              9,
              14,
              19,
              24,
              32
            ],
            "predicted_blue": [
              4,
              5,
              11
            ],
            "actual_red": [
              1,
              2,
              13,
              23,
              25,
              27
            ],
            "actual_blue": 5,
            "red_match": 1,
            "blue_match": 1,
            "prize": "六等奖(含)",
            "prize_amount": 35,
            "fortune_eligible": false,
            "fortune_amount": 0
          },
          {
            "period": "2026039",
            "predicted_red": [
              3,
              6,
              13,
              17,
              19,
              25,
              27
            ],
            "predicted_blue": [
              9,
              12,
              16
            ],
            "actual_red": [
              8,
              17,
              18,
              21,
              25,
              30
            ],
            "actual_blue": 5,
            "red_match": 2,
            "blue_match": 0,
            "prize": null,
            "prize_amount": 0,
            "fortune_eligible": false,
            "fortune_amount": 0
          },
          {
            "period": "2026040",
            "predicted_red": [
              5,
              7,
              10,
              16,
              25,
              30,
              33
            ],
            "predicted_blue": [
              10,
              14,
              16
            ],
            "actual_red": [
              3,
              4,
              14,
              22,
              23,
              33
            ],
            "actual_blue": 4,
            "red_match": 1,
            "blue_match": 0,
            "prize": null,
            "prize_amount": 0,
            "fortune_eligible": false,
            "fortune_amount": 0
          },
          {
            "period": "2026041",
            "predicted_red": [
              3,
              4,
              13,
              16,
              23,
              26,
              27
            ],
            "predicted_blue": [
              3,
              7,
              15
            ],
            "actual_red": [
              2,
              8,
              10,
              17,
              19,
              24
            ],
            "actual_blue": 13,
            "red_match": 0,
            "blue_match": 0,
            "prize": null,
            "prize_amount": 0,
            "fortune_eligible": false,
            "fortune_amount": 0
          }
        ],
        "fortune_stats": {
          "eligible_rate": 0.13,
          "profit_rate": 0.13,
          "total_fortune": 780,
          "total_cost": 4200,
          "net_fortune": -3420
        }
      },
      "连号感知": {
        "avg_red_match": 1.13,
        "blue_accuracy": 0.13,
        "distribution": {
          "0": 28,
          "1": 37,
          "2": 29,
          "3": 6
        },
        "details": [
          {
            "period": "2026037",
            "predicted_red": [
              1,
              2,
              3,
              13,
              15,
              22,
              28
            ],
            "predicted_blue": [
              1,
              2,
              7
            ],
            "actual_red": [
              11,
              22,
              27,
              29,
              31,
              33
            ],
            "actual_blue": 12,
            "red_match": 1,
            "blue_match": 0,
            "prize": null,
            "prize_amount": 0,
            "fortune_eligible": false,
            "fortune_amount": 0
          },
          {
            "period": "2026038",
            "predicted_red": [
              3,
              4,
              8,
              18,
              20,
              22,
              30
            ],
            "predicted_blue": [
              3,
              4,
              5
            ],
            "actual_red": [
              1,
              2,
              13,
              23,
              25,
              27
            ],
            "actual_blue": 5,
            "red_match": 0,
            "blue_match": 1,
            "prize": "六等奖(含)",
            "prize_amount": 35,
            "fortune_eligible": false,
            "fortune_amount": 0
          },
          {
            "period": "2026039",
            "predicted_red": [
              7,
              9,
              15,
              20,
              24,
              27,
              33
            ],
            "predicted_blue": [
              2,
              3,
              6
            ],
            "actual_red": [
              8,
              17,
              18,
              21,
              25,
              30
            ],
            "actual_blue": 5,
            "red_match": 0,
            "blue_match": 0,
            "prize": null,
            "prize_amount": 0,
            "fortune_eligible": false,
            "fortune_amount": 0
          },
          {
            "period": "2026040",
            "predicted_red": [
              2,
              3,
              4,
              5,
              8,
              16,
              21
            ],
            "predicted_blue": [
              4,
              9,
              13
            ],
            "actual_red": [
              3,
              4,
              14,
              22,
              23,
              33
            ],
            "actual_blue": 4,
            "red_match": 2,
            "blue_match": 1,
            "prize": "六等奖(含)",
            "prize_amount": 35,
            "fortune_eligible": false,
            "fortune_amount": 0
          },
          {
            "period": "2026041",
            "predicted_red": [
              9,
              10,
              12,
              13,
              15,
              17,
              25
            ],
            "predicted_blue": [
              2,
              6,
              11
            ],
            "actual_red": [
              2,
              8,
              10,
              17,
              19,
              24
            ],
            "actual_blue": 13,
            "red_match": 2,
            "blue_match": 0,
            "prize": null,
            "prize_amount": 0,
            "fortune_eligible": false,
            "fortune_amount": 0
          }
        ],
        "fortune_stats": {
          "eligible_rate": 0.06,
          "profit_rate": 0.06,
          "total_fortune": 360,
          "total_cost": 4200,
          "net_fortune": -3840
        }
      },
      "福运优化": {
        "avg_red_match": 1.47,
        "blue_accuracy": 0.15,
        "distribution": {
          "3": 11,
          "2": 29,
          "1": 40,
          "0": 16,
          "4": 4
        },
        "details": [
          {
            "period": "2026037",
            "predicted_red": [
              3,
              6,
              11,
              22,
              26,
              27,
              29
            ],
            "predicted_blue": [
              2,
              6,
              14
            ],
            "actual_red": [
              11,
              22,
              27,
              29,
              31,
              33
            ],
            "actual_blue": 12,
            "red_match": 4,
            "blue_match": 0,
            "prize": "四/五等奖(含)",
            "prize_amount": 30,
            "fortune_eligible": true,
            "fortune_amount": 60
          },
          {
            "period": "2026038",
            "predicted_red": [
              3,
              5,
              15,
              20,
              24,
              26,
              30
            ],
            "predicted_blue": [
              3,
              9,
              13
            ],
            "actual_red": [
              1,
              2,
              13,
              23,
              25,
              27
            ],
            "actual_blue": 5,
            "red_match": 0,
            "blue_match": 0,
            "prize": null,
            "prize_amount": 0,
            "fortune_eligible": false,
            "fortune_amount": 0
          },
          {
            "period": "2026039",
            "predicted_red": [
              4,
              7,
              16,
              23,
              24,
              25,
              32
            ],
            "predicted_blue": [
              3,
              9,
              12
            ],
            "actual_red": [
              8,
              17,
              18,
              21,
              25,
              30
            ],
            "actual_blue": 5,
            "red_match": 1,
            "blue_match": 0,
            "prize": null,
            "prize_amount": 0,
            "fortune_eligible": false,
            "fortune_amount": 0
          },
          {
            "period": "2026040",
            "predicted_red": [
              7,
              10,
              12,
              19,
              24,
              26,
              33
            ],
            "predicted_blue": [
              5,
              6,
              13
            ],
            "actual_red": [
              3,
              4,
              14,
              22,
              23,
              33
            ],
            "actual_blue": 4,
            "red_match": 1,
            "blue_match": 0,
            "prize": null,
            "prize_amount": 0,
            "fortune_eligible": false,
            "fortune_amount": 0
          },
          {
            "period": "2026041",
            "predicted_red": [
              3,
              7,
              8,
              14,
              24,
              29,
              33
            ],
            "predicted_blue": [
              3,
              8,
              13
            ],
            "actual_red": [
              2,
              8,
              10,
              17,
              19,
              24
            ],
            "actual_blue": 13,
            "red_match": 2,
            "blue_match": 1,
            "prize": "六等奖(含)",
            "prize_amount": 35,
            "fortune_eligible": false,
            "fortune_amount": 0
          }
        ],
        "fortune_stats": {
          "eligible_rate": 0.12,
          "profit_rate": 0.12,
          "total_fortune": 720,
          "total_cost": 4200,
          "net_fortune": -3480
        }
      }
    },
    "best_strategy": {
      "name": "福运优化",
      "avg_red_match": 1.47,
      "improvement": 0.1946
    },
    "ranking": [
      [
        "福运优化",
        1.47
      ],
      [
        "和值控制",
        1.36
      ],
      [
        "冷热混合",
        1.3
      ],
      [
        "三区均衡",
        1.22
      ],
      [
        "遗漏优先",
        1.2
      ],
      [
        "智能加权",
        1.15
      ],
      [
        "连号感知",
        1.13
      ]
    ]
  },
  "fortune": {
    "description": "福运优化 (7红3蓝)",
    "test_periods": 100,
    "ticket_cost": 42,
    "match_stats": {
      "avg_red_match": 1.32,
      "blue_accuracy": 0.25,
      "distribution": {
        "3": 11,
        "1": 45,
        "0": 17,
        "2": 27
      }
    },
    "fortune_stats": {
      "eligible_count": 5,
      "eligible_rate": 5.0,
      "eligible_rate_desc": "5/100 期触发福运奖"
    },
    "profit_stats": {
      "total_cost": 4200,
      "total_fortune": 300,
      "total_regular_prize": 905,
      "total_income": 1205,
      "net_profit": -2995,
      "roi": -71.31,
      "profit_periods": 5,
      "profit_rate": 5.0
    },
    "fortune_by_red_match": {
      "3": {
        "count": 11,
        "fortune_eligible": 5,
        "fortune_amount": 300
      },
      "1": {
        "count": 45,
        "fortune_eligible": 0,
        "fortune_amount": 0
      },
      "0": {
        "count": 17,
        "fortune_eligible": 0,
        "fortune_amount": 0
      },
      "2": {
        "count": 27,
        "fortune_eligible": 0,
        "fortune_amount": 0
      }
    },
    "details": [
      {
        "period": "2026032",
        "predicted_red": [
          2,
          4,
          20,
          21,
          24,
          27,
          31
        ],
        "predicted_blue": [
          4,
          9,
          13
        ],
        "actual_red": [
          1,
          3,
          11,
          18,
          31,
          33
        ],
        "actual_blue": 2,
        "red_match": 1,
        "blue_match": 0,
        "prize": null,
        "prize_amount": 0,
        "fortune_eligible": false,
        "fortune_amount": 0
      },
      {
        "period": "2026033",
        "predicted_red": [
          1,
          7,
          8,
          15,
          20,
          21,
          32
        ],
        "predicted_blue": [
          4,
          10,
          11
        ],
        "actual_red": [
          3,
          6,
          13,
          21,
          28,
          29
        ],
        "actual_blue": 6,
        "red_match": 1,
        "blue_match": 0,
        "prize": null,
        "prize_amount": 0,
        "fortune_eligible": false,
        "fortune_amount": 0
      },
      {
        "period": "2026034",
        "predicted_red": [
          4,
          8,
          11,
          21,
          23,
          32,
          33
        ],
        "predicted_blue": [
          5,
          9,
          11
        ],
        "actual_red": [
          1,
          3,
          7,
          13,
          22,
          23
        ],
        "actual_blue": 7,
        "red_match": 1,
        "blue_match": 0,
        "prize": null,
        "prize_amount": 0,
        "fortune_eligible": false,
        "fortune_amount": 0
      },
      {
        "period": "2026035",
        "predicted_red": [
          5,
          10,
          13,
          22,
          24,
          29,
          33
        ],
        "predicted_blue": [
          3,
          9,
          14
        ],
        "actual_red": [
          2,
          6,
          12,
          24,
          25,
          32
        ],
        "actual_blue": 2,
        "red_match": 1,
        "blue_match": 0,
        "prize": null,
        "prize_amount": 0,
        "fortune_eligible": false,
        "fortune_amount": 0
      },
      {
        "period": "2026036",
        "predicted_red": [
          4,
          7,
          12,
          15,
          18,
          23,
          33
        ],
        "predicted_blue": [
          5,
          9,
          16
        ],
        "actual_red": [
          6,
          10,
          12,
          15,
          22,
          28
        ],
        "actual_blue": 8,
        "red_match": 2,
        "blue_match": 0,
        "prize": null,
        "prize_amount": 0,
        "fortune_eligible": false,
        "fortune_amount": 0
      },
      {
        "period": "2026037",
        "predicted_red": [
          4,
          7,
          10,
          21,
          22,
          25,
          27
        ],
        "predicted_blue": [
          4,
          9,
          11
        ],
        "actual_red": [
          11,
          22,
          27,
          29,
          31,
          33
        ],
        "actual_blue": 12,
        "red_match": 2,
        "blue_match": 0,
        "prize": null,
        "prize_amount": 0,
        "fortune_eligible": false,
        "fortune_amount": 0
      },
      {
        "period": "2026038",
        "predicted_red": [
          4,
          9,
          13,
          20,
          26,
          27,
          31
        ],
        "predicted_blue": [
          4,
          7,
          13
        ],
        "actual_red": [
          1,
          2,
          13,
          23,
          25,
          27
        ],
        "actual_blue": 5,
        "red_match": 2,
        "blue_match": 0,
        "prize": null,
        "prize_amount": 0,
        "fortune_eligible": false,
        "fortune_amount": 0
      },
      {
        "period": "2026039",
        "predicted_red": [
          4,
          5,
          16,
          18,
          21,
          30,
          33
        ],
        "predicted_blue": [
          3,
          9,
          15
        ],
        "actual_red": [
          8,
          17,
          18,
          21,
          25,
          30
        ],
        "actual_blue": 5,
        "red_match": 3,
        "blue_match": 0,
        "prize": null,
        "prize_amount": 0,
        "fortune_eligible": true,
        "fortune_amount": 60
      },
      {
        "period": "2026040",
        "predicted_red": [
          2,
          4,
          7,
          19,
          20,
          27,
          31
        ],
        "predicted_blue": [
          1,
          9,
          11
        ],
        "actual_red": [
          3,
          4,
          14,
          22,
          23,
          33
        ],
        "actual_blue": 4,
        "red_match": 1,
        "blue_match": 0,
        "prize": null,
        "prize_amount": 0,
        "fortune_eligible": false,
        "fortune_amount": 0
      },
      {
        "period": "2026041",
        "predicted_red": [
          1,
          10,
          17,
          20,
          22,
          25,
          32
        ],
        "predicted_blue": [
          5,
          7,
          13
        ],
        "actual_red": [
          2,
          8,
          10,
          17,
          19,
          24
        ],
        "actual_blue": 13,
        "red_match": 2,
        "blue_match": 1,
        "prize": "六等奖(含)",
        "prize_amount": 35,
        "fortune_eligible": false,
        "fortune_amount": 0
      }
    ],
    "summary": {
      "conclusion": "亏损",
      "avg_per_period": -29.95,
      "fortune_contribution": 24.9
    }
  },
  "avg_red_match": 1.26,
  "avg_random_match": 1.0907,
  "improvement": 0.1693,
  "improvement_percent": 15.52,
  "blue_accuracy": 0.02,
  "distribution": {
    "1": 41,
    "2": 24,
    "0": 23,
    "3": 11,
    "4": 1
  },
  "details": [
    {
      "period": "2026037",
      "predicted_red": [
        3,
        9,
        18,
        22,
        23,
        24
      ],
      "predicted_blue": 16,
      "actual_red": [
        11,
        22,
        27,
        29,
        31,
        33
      ],
      "actual_blue": 12,
      "red_match": 1,
      "blue_match": 0,
      "prize": null,
      "prize_amount": 0,
      "fortune_eligible": false,
      "fortune_amount": 0
    },
    {
      "period": "2026038",
      "predicted_red": [
        3,
        10,
        11,
        22,
        26,
        30
      ],
      "predicted_blue": 10,
      "actual_red": [
        1,
        2,
        13,
        23,
        25,
        27
      ],
      "actual_blue": 5,
      "red_match": 0,
      "blue_match": 0,
      "prize": null,
      "prize_amount": 0,
      "fortune_eligible": false,
      "fortune_amount": 0
    },
    {
      "period": "2026039",
      "predicted_red": [
        7,
        17,
        18,
        21,
        22,
        23
      ],
      "predicted_blue": 6,
      "actual_red": [
        8,
        17,
        18,
        21,
        25,
        30
      ],
      "actual_blue": 5,
      "red_match": 3,
      "blue_match": 0,
      "prize": null,
      "prize_amount": 0,
      "fortune_eligible": true,
      "fortune_amount": 5
    },
    {
      "period": "2026040",
      "predicted_red": [
        3,
        16,
        22,
        23,
        27,
        32
      ],
      "predicted_blue": 14,
      "actual_red": [
        3,
        4,
        14,
        22,
        23,
        33
      ],
      "actual_blue": 4,
      "red_match": 3,
      "blue_match": 0,
      "prize": null,
      "prize_amount": 0,
      "fortune_eligible": true,
      "fortune_amount": 5
    },
    {
      "period": "2026041",
      "predicted_red": [
        2,
        8,
        11,
        12,
        19,
        33
      ],
      "predicted_blue": 1,
      "actual_red": [
        2,
        8,
        10,
        17,
        19,
        24
      ],
      "actual_blue": 13,
      "red_match": 3,
      "blue_match": 0,
      "prize": null,
      "prize_amount": 0,
      "fortune_eligible": true,
      "fortune_amount": 5
    }
  ],
  "best_strategy_name": "连号感知",
  "ranking": [
    [
      "智能加权",
      0.87
    ],
    [
      "三区均衡",
      1.18
    ],
    [
      "冷热混合",
      1.07
    ],
    [
      "遗漏优先",
      0.91
    ],
    [
      "和值控制",
      1.09
    ],
    [
      "连号感知",
      1.26
    ]
  ]
}