{
  "generated_at": "2026-04-07T15:56:20.401329",
  "based_on_period": "2026038",
  "based_on_date": "2026-04-07",
  "total_history": 3435,
  "single": {
    "description": "单式投注 (6红1蓝)",
    "red_count": 6,
    "blue_count": 1,
    "predictions": [
      {
        "id": 1,
        "strategy": "智能加权",
        "red": [
          9,
          18,
          21,
          23,
          24,
          33
        ],
        "blue": 16,
        "red_count": 6,
        "blue_count": 1,
        "sum": 128,
        "span": 24,
        "odd_count": 4,
        "big_count": 5,
        "zone_dist": "1:2:3",
        "meta": {
          "method": "weighted"
        }
      },
      {
        "id": 2,
        "strategy": "三区均衡",
        "red": [
          5,
          11,
          13,
          19,
          24,
          29
        ],
        "blue": 1,
        "red_count": 6,
        "blue_count": 1,
        "sum": 101,
        "span": 24,
        "odd_count": 5,
        "big_count": 3,
        "zone_dist": "2:2:2",
        "meta": {
          "method": "zone_balanced",
          "zone_dist": [
            2,
            2,
            2
          ]
        }
      },
      {
        "id": 3,
        "strategy": "冷热混合",
        "red": [
          6,
          13,
          14,
          22,
          24,
          25
        ],
        "blue": 9,
        "red_count": 6,
        "blue_count": 1,
        "sum": 104,
        "span": 19,
        "odd_count": 2,
        "big_count": 3,
        "zone_dist": "1:3:2",
        "meta": {
          "method": "cold_hot_mix",
          "ratio": "3热:2温:1冷"
        }
      },
      {
        "id": 4,
        "strategy": "遗漏优先",
        "red": [
          5,
          14,
          17,
          19,
          20,
          26
        ],
        "blue": 11,
        "red_count": 6,
        "blue_count": 1,
        "sum": 101,
        "span": 21,
        "odd_count": 3,
        "big_count": 4,
        "zone_dist": "1:4:1",
        "meta": {
          "method": "missing_focused"
        }
      },
      {
        "id": 5,
        "strategy": "和值控制",
        "red": [
          2,
          9,
          12,
          17,
          20,
          26
        ],
        "blue": 1,
        "red_count": 6,
        "blue_count": 1,
        "sum": 86,
        "span": 24,
        "odd_count": 2,
        "big_count": 3,
        "zone_dist": "2:3:1",
        "meta": {
          "method": "sum_controlled",
          "sum": 86,
          "target_range": [
            75,
            118
          ]
        }
      }
    ]
  },
  "duplex": {
    "description": "复式投注 (7红3蓝)",
    "red_count": 7,
    "blue_count": 3,
    "predictions": [
      {
        "id": 1,
        "strategy": "智能加权",
        "red": [
          2,
          7,
          9,
          13,
          18,
          24,
          31
        ],
        "blue": [
          3,
          4,
          7
        ],
        "red_count": 7,
        "blue_count": 3,
        "sum": 104,
        "span": 29,
        "odd_count": 4,
        "big_count": 3,
        "zone_dist": "3:2:2",
        "meta": {
          "method": "weighted"
        }
      },
      {
        "id": 2,
        "strategy": "三区均衡",
        "red": [
          1,
          9,
          16,
          18,
          19,
          24,
          25
        ],
        "blue": [
          1,
          14,
          16
        ],
        "red_count": 7,
        "blue_count": 3,
        "sum": 112,
        "span": 24,
        "odd_count": 4,
        "big_count": 4,
        "zone_dist": "2:3:2",
        "meta": {
          "method": "zone_balanced",
          "zone_dist": [
            2,
            3,
            2
          ]
        }
      },
      {
        "id": 3,
        "strategy": "冷热混合",
        "red": [
          1,
          2,
          14,
          23,
          24,
          26,
          30
        ],
        "blue": [
          4,
          8,
          10
        ],
        "red_count": 7,
        "blue_count": 3,
        "sum": 120,
        "span": 29,
        "odd_count": 2,
        "big_count": 4,
        "zone_dist": "2:1:4",
        "meta": {
          "method": "cold_hot_mix",
          "ratio": "3热:2温:2冷"
        }
      }
    ]
  },
  "fortune": {
    "description": "福运优化 (7红3蓝)",
    "red_count": 7,
    "blue_count": 3,
    "note": "针对福运奖优化，奖池≥15亿时收益最大化",
    "predictions": [
      {
        "id": 1,
        "strategy": "福运优化",
        "red": [
          1,
          4,
          15,
          20,
          27,
          30,
          31
        ],
        "blue": [
          2,
          9,
          15
        ],
        "red_count": 7,
        "blue_count": 3,
        "sum": 128,
        "span": 30,
        "odd_count": 4,
        "big_count": 4,
        "zone_dist": "2:2:3",
        "meta": {
          "method": "fortune_optimized",
          "combination_score": "97/100",
          "search_attempts": 3,
          "expand_notes": "7+3 复式 → 21注 = 42元",
          "red_structure": {
            "sum": 128,
            "target_sum": 119,
            "odd_even": "4奇:3偶",
            "zone_distribution": "2:2:3",
            "consecutive_pairs": 1,
            "tail_digit_types": 5,
            "cold_numbers": [
              4,
              20,
              30
            ],
            "warm_numbers": [
              1,
              15,
              27,
              31
            ],
            "hot_numbers": []
          },
          "pool_info": {
            "analysis_window": "最近100期",
            "cold_pool_size": 8,
            "warm_pool_size": 21,
            "hot_pool_size": 4
          },
          "fortune_prize": {
            "activation": "奖池≥15亿自动激活",
            "x3_y0_scenario": "12注×5元=60元",
            "cost": "42元",
            "net_profit": "+18元"
          }
        }
      },
      {
        "id": 2,
        "strategy": "福运优化",
        "red": [
          4,
          11,
          15,
          18,
          20,
          29,
          30
        ],
        "blue": [
          4,
          6,
          14
        ],
        "red_count": 7,
        "blue_count": 3,
        "sum": 127,
        "span": 26,
        "odd_count": 3,
        "big_count": 4,
        "zone_dist": "2:3:2",
        "meta": {
          "method": "fortune_optimized",
          "combination_score": "93/100",
          "search_attempts": 6,
          "expand_notes": "7+3 复式 → 21注 = 42元",
          "red_structure": {
            "sum": 127,
            "target_sum": 119,
            "odd_even": "3奇:4偶",
            "zone_distribution": "2:3:2",
            "consecutive_pairs": 1,
            "tail_digit_types": 6,
            "cold_numbers": [
              4,
              20,
              29,
              30
            ],
            "warm_numbers": [
              11,
              15,
              18
            ],
            "hot_numbers": []
          },
          "pool_info": {
            "analysis_window": "最近100期",
            "cold_pool_size": 8,
            "warm_pool_size": 21,
            "hot_pool_size": 4
          },
          "fortune_prize": {
            "activation": "奖池≥15亿自动激活",
            "x3_y0_scenario": "12注×5元=60元",
            "cost": "42元",
            "net_profit": "+18元"
          }
        }
      },
      {
        "id": 3,
        "strategy": "福运优化",
        "red": [
          6,
          7,
          12,
          17,
          21,
          24,
          29
        ],
        "blue": [
          4,
          7,
          15
        ],
        "red_count": 7,
        "blue_count": 3,
        "sum": 116,
        "span": 23,
        "odd_count": 4,
        "big_count": 4,
        "zone_dist": "2:3:2",
        "meta": {
          "method": "fortune_optimized",
          "combination_score": "100/100",
          "search_attempts": 4,
          "expand_notes": "7+3 复式 → 21注 = 42元",
          "red_structure": {
            "sum": 116,
            "target_sum": 119,
            "odd_even": "4奇:3偶",
            "zone_distribution": "2:3:2",
            "consecutive_pairs": 1,
            "tail_digit_types": 6,
            "cold_numbers": [
              7,
              21,
              29
            ],
            "warm_numbers": [
              6,
              12,
              17,
              24
            ],
            "hot_numbers": []
          },
          "pool_info": {
            "analysis_window": "最近100期",
            "cold_pool_size": 8,
            "warm_pool_size": 21,
            "hot_pool_size": 4
          },
          "fortune_prize": {
            "activation": "奖池≥15亿自动激活",
            "x3_y0_scenario": "12注×5元=60元",
            "cost": "42元",
            "net_profit": "+18元"
          }
        }
      }
    ]
  },
  "predictions": [
    {
      "id": 1,
      "strategy": "智能加权",
      "red": [
        9,
        18,
        21,
        23,
        24,
        33
      ],
      "blue": 16,
      "red_count": 6,
      "blue_count": 1,
      "sum": 128,
      "span": 24,
      "odd_count": 4,
      "big_count": 5,
      "zone_dist": "1:2:3",
      "meta": {
        "method": "weighted"
      }
    },
    {
      "id": 2,
      "strategy": "三区均衡",
      "red": [
        5,
        11,
        13,
        19,
        24,
        29
      ],
      "blue": 1,
      "red_count": 6,
      "blue_count": 1,
      "sum": 101,
      "span": 24,
      "odd_count": 5,
      "big_count": 3,
      "zone_dist": "2:2:2",
      "meta": {
        "method": "zone_balanced",
        "zone_dist": [
          2,
          2,
          2
        ]
      }
    },
    {
      "id": 3,
      "strategy": "冷热混合",
      "red": [
        6,
        13,
        14,
        22,
        24,
        25
      ],
      "blue": 9,
      "red_count": 6,
      "blue_count": 1,
      "sum": 104,
      "span": 19,
      "odd_count": 2,
      "big_count": 3,
      "zone_dist": "1:3:2",
      "meta": {
        "method": "cold_hot_mix",
        "ratio": "3热:2温:1冷"
      }
    },
    {
      "id": 4,
      "strategy": "遗漏优先",
      "red": [
        5,
        14,
        17,
        19,
        20,
        26
      ],
      "blue": 11,
      "red_count": 6,
      "blue_count": 1,
      "sum": 101,
      "span": 21,
      "odd_count": 3,
      "big_count": 4,
      "zone_dist": "1:4:1",
      "meta": {
        "method": "missing_focused"
      }
    },
    {
      "id": 5,
      "strategy": "和值控制",
      "red": [
        2,
        9,
        12,
        17,
        20,
        26
      ],
      "blue": 1,
      "red_count": 6,
      "blue_count": 1,
      "sum": 86,
      "span": 24,
      "odd_count": 2,
      "big_count": 3,
      "zone_dist": "2:3:1",
      "meta": {
        "method": "sum_controlled",
        "sum": 86,
        "target_range": [
          75,
          118
        ]
      }
    }
  ]
}